ezodbc/__init__.py
ezodbc/__version__.py
ezodbc/core.py
ezodbc/profiles.py
ezodbc/test.py
ezodbc/ui.py
ezodbc-0.2.4.dist-info/LICENSE
ezodbc-0.2.4.dist-info/METADATA
ezodbc-0.2.4.dist-info/WHEEL
ezodbc-0.2.4.dist-info/top_level.txt
ezodbc-0.2.4.dist-info/RECORD
