Metadata-Version: 2.1
Name: ezodbc
Version: 0.2.4
Summary: easy and secure ODBC connections for analysis with Pandas. No more hard-coded credentials or any of those darn environment variables!
Home-page: https://github.com/brontomerus/ezodbc
Author: Brandon Donelan
Author-email: brandon.donelan@outlook.com
License: MIT
Platform: UNKNOWN
Classifier: License :: OSI Approved :: MIT License
Classifier: Programming Language :: Python
Classifier: Programming Language :: Python :: 3
Classifier: Programming Language :: Python :: 3.6
Classifier: Programming Language :: Python :: Implementation :: CPython
Classifier: Programming Language :: Python :: Implementation :: PyPy
Requires-Python: >=3.6.0
Requires-Dist: SQLAlchemy (>=1.3.20)
Requires-Dist: pandas (>=1.0.0)
Requires-Dist: toml
Provides-Extra: dev
Requires-Dist: pytest (>=3.5.1) ; extra == 'dev'
Requires-Dist: pytest-cov (>=2.6.0) ; extra == 'dev'
